gitrun/__init__.py
gitrun/__main__.py
gitrun/cli.py
gitrun/core.py
gitrun/utils.py
gitrun-0.2.0.dist-info/licenses/LICENSE
tests/__init__.py
tests/test_core.py
gitrun-0.2.0.dist-info/METADATA
gitrun-0.2.0.dist-info/WHEEL
gitrun-0.2.0.dist-info/entry_points.txt
gitrun-0.2.0.dist-info/top_level.txt
gitrun-0.2.0.dist-info/RECORD
