Metadata-Version: 2.4
Name: gitrun
Version: 0.2.0
License-File: LICENSE
Requires-Dist: requests>=2.25.0
Dynamic: license-file
Dynamic: requires-dist
